karls_chatgpt_helpers/__init__.py
karls_chatgpt_helpers/helpers.py
karls_chatgpt_helpers/chatgpt/__init__.py
karls_chatgpt_helpers/chatgpt/__main__.py
karls_chatgpt_helpers/gptshell/__init__.py
karls_chatgpt_helpers/gptshell/__main__.py
karls_chatgpt_helpers-0.0.3.dist-info/LICENSE.md
karls_chatgpt_helpers-0.0.3.dist-info/METADATA
karls_chatgpt_helpers-0.0.3.dist-info/WHEEL
karls_chatgpt_helpers-0.0.3.dist-info/entry_points.txt
karls_chatgpt_helpers-0.0.3.dist-info/top_level.txt
karls_chatgpt_helpers-0.0.3.dist-info/RECORD
