Metadata-Version: 2.1
Name: karls-chatgpt-helpers
Version: 0.0.3
Summary: Helper functions for chatgpt
Home-page: https://github.com/lehenbauer/karls_chatgpt_helpers
Author: Karl Lehenbauer
Author-email: Karl <support@lehenbauer.com>
License: Copyright © 2023 Karl Lehenbauer
Project-URL: Homepage, https://github.com/lehenbauer/karls-chatgpt-helpers
Project-URL: Bug Tracker, https://github.com/lehenbauer/karls-chatgpt-helpers/issues
Classifier: Development Status :: 3 - Alpha
Classifier: Intended Audience :: Developers
Classifier: License :: OSI Approved :: BSD License
Classifier: Programming Language :: Python :: 3
Classifier: Programming Language :: Python :: 3.7
Classifier: Programming Language :: Python :: 3.8
Classifier: Programming Language :: Python :: 3.9
Requires-Python: >=3.7
License-File: LICENSE.md
Requires-Dist: openai
Requires-Dist: pyyaml
